dacpy/__init__.py
dacpy/__version__.py
dacpy/main.py
dacpy/py.typed
dacpy/settings.py
dacpy/sync.py
dacpy-0.1.0.dist-info/METADATA
dacpy-0.1.0.dist-info/WHEEL
dacpy-0.1.0.dist-info/entry_points.txt
dacpy-0.1.0.dist-info/RECORD
